sorampt/__init__.py
sorampt/__main__.py
sorampt/cli/__init__.py
sorampt/cli/_options.py
sorampt/cli/checkbox.py
sorampt/cli/confirm.py
sorampt/cli/input.py
sorampt/cli/list.py
sorampt/prompts/__init__.py
sorampt/prompts/_base.py
sorampt/prompts/_choice.py
sorampt/prompts/checkbox.py
sorampt/prompts/confirm.py
sorampt/prompts/input.py
sorampt/prompts/list.py
sorampt/py.typed
sorampt/utils.py
sorampt-0.1.6.dist-info/LICENSE
sorampt-0.1.6.dist-info/METADATA
sorampt-0.1.6.dist-info/WHEEL
sorampt-0.1.6.dist-info/entry_points.txt
sorampt-0.1.6.dist-info/RECORD
