Metadata-Version: 2.1
Name: sorampt
Version: 0.1.6
Summary: 用于控制台交互的提示工具包
Home-page: https://github.com/netsora/sorampt
License: MIT
Keywords: prompt,inquirer,prompt-toolkit
Author: mute231010
Author-email: mute231010@gmail.com
Requires-Python: >=3.10,<4.0
Classifier: License :: OSI Approved :: MIT License
Classifier: Programming Language :: Python :: 3
Classifier: Programming Language :: Python :: 3.10
Classifier: Programming Language :: Python :: 3.11
Requires-Dist: prompt-toolkit (>=3.0.19,<4.0.0)
Project-URL: Documentation, https://github.com/netsora/sorampt
Project-URL: Repository, https://github.com/netsora/sorampt
